aiomcstats/__init__.py
aiomcstats/bedrock.py
aiomcstats/connection.py
aiomcstats/main.py
aiomcstats/models/__init__.py
aiomcstats/models/bedrock.py
aiomcstats/models/java.py
aiomcstats/ping.py
aiomcstats/utils.py
aiomcstats-0.1.3.dist-info/LICENSE
aiomcstats-0.1.3.dist-info/WHEEL
aiomcstats-0.1.3.dist-info/METADATA
aiomcstats-0.1.3.dist-info/RECORD
