Metadata-Version: 2.1
Name: aiomcstats
Version: 0.1.3
Summary: Asyncpixel
Home-page: https://github.com/Obsidion-dev/aiomcstats
License: GPL-3.0-or-later
Author: Leon Bowie
Author-email: leon@bowie-co.nz
Requires-Python: >=3.8,<4.0
Classifier: License :: OSI Approved :: GNU General Public License v3 or later (GPLv3+)
Classifier: Programming Language :: Python :: 3
Classifier: Programming Language :: Python :: 3.8
Classifier: Programming Language :: Python :: 3.9
Requires-Dist: asyncio-dgram (>=1.2.0,<2.0.0)
Requires-Dist: dnspython (>=2.1.0,<3.0.0)
Requires-Dist: pydantic (>=1.7.3,<2.0.0)
Project-URL: Changelog, https://github.com/Obsidion-dev/aiomcstats/releases
Project-URL: Documentation, https://aiomcstats.readthedocs.io
Project-URL: Repository, https://github.com/Obsidion-dev/aiomcstats
